[
  {
    "id": 60,
    "name": "Calypso",
    "status": "Dead",
    "species": "Human",
    "location": {
      "name": "unknown",
      "url": ""
    },
    "image": "https://raw.githubusercontent.com/iswilljr/rick-and-morty-api/master/src/images/60.jpeg",
    "episode": {
      "name": "Vindicators 3: The Return of Worldender",
      "url": "https://therickandmortyapi.vercel.app/api/episode/25"
    },
    "url": "https://therickandmortyapi.vercel.app/api/character/60"
  },
  {
    "id": 75,
    "name": "Courier Flap",
    "status": "Alive",
    "species": "Alien",
    "location": {
      "name": "Planet Squanch",
      "url": "https://therickandmortyapi.vercel.app/api/location/35"
    },
    "image": "https://raw.githubusercontent.com/iswilljr/rick-and-morty-api/master/src/images/75.jpeg",
    "episode": {
      "name": "The Wedding Squanchers",
      "url": "https://therickandmortyapi.vercel.app/api/episode/21"
    },
    "url": "https://therickandmortyapi.vercel.app/api/character/75"
  },
  {
    "id": 230,
    "name": "Morty Jr.",
    "status": "Alive",
    "species": "Humanoid",
    "location": {
      "name": "Earth (Replacement Dimension)",
      "url": "https://therickandmortyapi.vercel.app/api/location/20"
    },
    "image": "https://raw.githubusercontent.com/iswilljr/rick-and-morty-api/master/src/images/230.jpeg",
    "episode": {
      "name": "Raising Gazorpazorp",
      "url": "https://therickandmortyapi.vercel.app/api/episode/7"
    },
    "url": "https://therickandmortyapi.vercel.app/api/character/230"
  },
  {
    "id": 458,
    "name": "Tax Attorney",
    "status": "unknown",
    "species": "Human",
    "location": {
      "name": "Interdimensional Cable",
      "url": "https://therickandmortyapi.vercel.app/api/location/6"
    },
    "image": "https://raw.githubusercontent.com/iswilljr/rick-and-morty-api/master/src/images/458.jpeg",
    "episode": {
      "name": "Interdimensional Cable 2: Tempting Fate",
      "url": "https://therickandmortyapi.vercel.app/api/episode/19"
    },
    "url": "https://therickandmortyapi.vercel.app/api/character/458"
  },
  {
    "id": 534,
    "name": "Tony's Dad",
    "status": "Alive",
    "species": "Alien",
    "location": {
      "name": "Earth (Replacement Dimension)",
      "url": "https://therickandmortyapi.vercel.app/api/location/20"
    },
    "image": "https://raw.githubusercontent.com/iswilljr/rick-and-morty-api/master/src/images/534.jpeg",
    "episode": {
      "name": "The Old Man and the Seat",
      "url": "https://therickandmortyapi.vercel.app/api/episode/33"
    },
    "url": "https://therickandmortyapi.vercel.app/api/character/534"
  },
  {
    "id": 645,
    "name": "Shane",
    "status": "unknown",
    "species": "Alien",
    "location": {
      "name": "Glorzo Asteroid",
      "url": "https://therickandmortyapi.vercel.app/api/location/101"
    },
    "image": "https://raw.githubusercontent.com/iswilljr/rick-and-morty-api/master/src/images/645.jpeg",
    "episode": {
      "name": "Promortyus",
      "url": "https://therickandmortyapi.vercel.app/api/episode/38"
    },
    "url": "https://therickandmortyapi.vercel.app/api/character/645"
  }
]
