[
  {
    "id": 244,
    "name": "Mr. Poopybutthole",
    "status": "Alive",
    "species": "Poopybutthole",
    "location": {
      "name": "Earth (Replacement Dimension)",
      "url": "https://therickandmortyapi.vercel.app/api/location/20"
    },
    "image": "https://raw.githubusercontent.com/iswilljr/rick-and-morty-api/master/src/images/244.jpeg",
    "episode": {
      "name": "Total Rickall",
      "url": "https://therickandmortyapi.vercel.app/api/episode/15"
    },
    "url": "https://therickandmortyapi.vercel.app/api/character/244"
  },
  {
    "id": 285,
    "name": "Rick Prime",
    "status": "Dead",
    "species": "Human",
    "location": {
      "name": "Citadel of Ricks",
      "url": "https://therickandmortyapi.vercel.app/api/location/3"
    },
    "image": "https://raw.githubusercontent.com/iswilljr/rick-and-morty-api/master/src/images/285.jpeg",
    "episode": {
      "name": "The Rickshank Rickdemption",
      "url": "https://therickandmortyapi.vercel.app/api/episode/22"
    },
    "url": "https://therickandmortyapi.vercel.app/api/character/285"
  },
  {
    "id": 370,
    "name": "Two Guys with Handlebar Mustaches",
    "status": "Alive",
    "species": "Human",
    "location": {
      "name": "Interdimensional Cable",
      "url": "https://therickandmortyapi.vercel.app/api/location/6"
    },
    "image": "https://raw.githubusercontent.com/iswilljr/rick-and-morty-api/master/src/images/370.jpeg",
    "episode": {
      "name": "Rixty Minutes",
      "url": "https://therickandmortyapi.vercel.app/api/episode/8"
    },
    "url": "https://therickandmortyapi.vercel.app/api/character/370"
  },
  {
    "id": 434,
    "name": "Super Weird Rick",
    "status": "unknown",
    "species": "Human",
    "location": {
      "name": "unknown",
      "url": ""
    },
    "image": "https://raw.githubusercontent.com/iswilljr/rick-and-morty-api/master/src/images/434.jpeg",
    "episode": {
      "name": "Close Rick-counters of the Rick Kind",
      "url": "https://therickandmortyapi.vercel.app/api/episode/10"
    },
    "url": "https://therickandmortyapi.vercel.app/api/character/434"
  },
  {
    "id": 617,
    "name": "Phoenixperson",
    "status": "Alive",
    "species": "Alien",
    "location": {
      "name": "Story Train",
      "url": "https://therickandmortyapi.vercel.app/api/location/96"
    },
    "image": "https://raw.githubusercontent.com/iswilljr/rick-and-morty-api/master/src/images/617.jpeg",
    "episode": {
      "name": "Never Ricking Morty",
      "url": "https://therickandmortyapi.vercel.app/api/episode/37"
    },
    "url": "https://therickandmortyapi.vercel.app/api/character/617"
  },
  {
    "id": 649,
    "name": "Crystal Dealer",
    "status": "Dead",
    "species": "Alien",
    "location": {
      "name": "Alien Acid Plant",
      "url": "https://therickandmortyapi.vercel.app/api/location/102"
    },
    "image": "https://raw.githubusercontent.com/iswilljr/rick-and-morty-api/master/src/images/649.jpeg",
    "episode": {
      "name": "The Vat of Acid Episode",
      "url": "https://therickandmortyapi.vercel.app/api/episode/39"
    },
    "url": "https://therickandmortyapi.vercel.app/api/character/649"
  }
]
