[
  {
    "id": 145,
    "name": "Glenn",
    "status": "Alive",
    "species": "Human",
    "location": {
      "name": "Interdimensional Cable",
      "url": "https://therickandmortyapi.vercel.app/api/location/6"
    },
    "image": "https://raw.githubusercontent.com/iswilljr/rick-and-morty-api/master/src/images/145.jpeg",
    "episode": {
      "name": "Rixty Minutes",
      "url": "https://therickandmortyapi.vercel.app/api/episode/8"
    },
    "url": "https://therickandmortyapi.vercel.app/api/character/145"
  },
  {
    "id": 410,
    "name": "Two Brothers",
    "status": "Alive",
    "species": "Human",
    "location": {
      "name": "Interdimensional Cable",
      "url": "https://therickandmortyapi.vercel.app/api/location/6"
    },
    "image": "https://raw.githubusercontent.com/iswilljr/rick-and-morty-api/master/src/images/410.jpeg",
    "episode": {
      "name": "Rixty Minutes",
      "url": "https://therickandmortyapi.vercel.app/api/episode/8"
    },
    "url": "https://therickandmortyapi.vercel.app/api/character/410"
  },
  {
    "id": 509,
    "name": "Bully",
    "status": "unknown",
    "species": "Human",
    "location": {
      "name": "Earth (Replacement Dimension)",
      "url": "https://therickandmortyapi.vercel.app/api/location/20"
    },
    "image": "https://raw.githubusercontent.com/iswilljr/rick-and-morty-api/master/src/images/509.jpeg",
    "episode": {
      "name": "Edge of Tomorty: Rick, Die, Rickpeat",
      "url": "https://therickandmortyapi.vercel.app/api/episode/32"
    },
    "url": "https://therickandmortyapi.vercel.app/api/character/509"
  },
  {
    "id": 539,
    "name": "Richard",
    "status": "Alive",
    "species": "Human",
    "location": {
      "name": "Earth (Replacement Dimension)",
      "url": "https://therickandmortyapi.vercel.app/api/location/20"
    },
    "image": "https://raw.githubusercontent.com/iswilljr/rick-and-morty-api/master/src/images/539.jpeg",
    "episode": {
      "name": "The Old Man and the Seat",
      "url": "https://therickandmortyapi.vercel.app/api/episode/33"
    },
    "url": "https://therickandmortyapi.vercel.app/api/character/539"
  },
  {
    "id": 718,
    "name": "Daphne",
    "status": "Alive",
    "species": "Alien",
    "location": {
      "name": "Ferkus 9",
      "url": "https://therickandmortyapi.vercel.app/api/location/113"
    },
    "image": "https://raw.githubusercontent.com/iswilljr/rick-and-morty-api/master/src/images/718.jpeg",
    "episode": {
      "name": "A Rickconvenient Mort",
      "url": "https://therickandmortyapi.vercel.app/api/episode/44"
    },
    "url": "https://therickandmortyapi.vercel.app/api/character/718"
  },
  {
    "id": 752,
    "name": "Changeformer",
    "status": "Dead",
    "species": "Robot",
    "location": {
      "name": "Space Tahoe",
      "url": "https://therickandmortyapi.vercel.app/api/location/118"
    },
    "image": "https://raw.githubusercontent.com/iswilljr/rick-and-morty-api/master/src/images/752.jpeg",
    "episode": {
      "name": "Amortycan Grickfitti",
      "url": "https://therickandmortyapi.vercel.app/api/episode/46"
    },
    "url": "https://therickandmortyapi.vercel.app/api/character/752"
  }
]
