[
  {
    "id": 589,
    "name": "Snake Reporter",
    "status": "Alive",
    "species": "Animal",
    "location": {
      "name": "Snake Planet",
      "url": "https://therickandmortyapi.vercel.app/api/location/78"
    },
    "image": "https://raw.githubusercontent.com/iswilljr/rick-and-morty-api/master/src/images/589.jpeg",
    "episode": {
      "name": "Rattlestar Ricklactica",
      "url": "https://therickandmortyapi.vercel.app/api/episode/36"
    },
    "url": "https://therickandmortyapi.vercel.app/api/character/589"
  },
  {
    "id": 591,
    "name": "High Pilot",
    "status": "unknown",
    "species": "Human",
    "location": {
      "name": "Earth (Replacement Dimension)",
      "url": "https://therickandmortyapi.vercel.app/api/location/20"
    },
    "image": "https://raw.githubusercontent.com/iswilljr/rick-and-morty-api/master/src/images/591.jpeg",
    "episode": {
      "name": "Rattlestar Ricklactica",
      "url": "https://therickandmortyapi.vercel.app/api/episode/36"
    },
    "url": "https://therickandmortyapi.vercel.app/api/character/591"
  },
  {
    "id": 632,
    "name": "Train Cop",
    "status": "Dead",
    "species": "Human",
    "location": {
      "name": "Story Train",
      "url": "https://therickandmortyapi.vercel.app/api/location/96"
    },
    "image": "https://raw.githubusercontent.com/iswilljr/rick-and-morty-api/master/src/images/632.jpeg",
    "episode": {
      "name": "Never Ricking Morty",
      "url": "https://therickandmortyapi.vercel.app/api/episode/37"
    },
    "url": "https://therickandmortyapi.vercel.app/api/character/632"
  },
  {
    "id": 671,
    "name": "New Improved Galactic Federation Guard",
    "status": "Dead",
    "species": "Alien",
    "location": {
      "name": "NX-5 Planet Remover",
      "url": "https://therickandmortyapi.vercel.app/api/location/105"
    },
    "image": "https://raw.githubusercontent.com/iswilljr/rick-and-morty-api/master/src/images/671.jpeg",
    "episode": {
      "name": "Star Mort: Rickturn of the Jerri",
      "url": "https://therickandmortyapi.vercel.app/api/episode/41"
    },
    "url": "https://therickandmortyapi.vercel.app/api/character/671"
  },
  {
    "id": 764,
    "name": "Jackey",
    "status": "Alive",
    "species": "Human",
    "location": {
      "name": "Earth (Replacement Dimension)",
      "url": "https://therickandmortyapi.vercel.app/api/location/20"
    },
    "image": "https://raw.githubusercontent.com/iswilljr/rick-and-morty-api/master/src/images/764.jpeg",
    "episode": {
      "name": "Rick & Morty's Thanksploitation Spectacular",
      "url": "https://therickandmortyapi.vercel.app/api/episode/47"
    },
    "url": "https://therickandmortyapi.vercel.app/api/character/764"
  },
  {
    "id": 794,
    "name": "Samansky",
    "status": "Dead",
    "species": "Alien",
    "location": {
      "name": "Earth (Replacement Dimension)",
      "url": "https://therickandmortyapi.vercel.app/api/location/20"
    },
    "image": "https://raw.githubusercontent.com/iswilljr/rick-and-morty-api/master/src/images/794.jpeg",
    "episode": {
      "name": "Gotron Jerrysis Rickvangelion",
      "url": "https://therickandmortyapi.vercel.app/api/episode/48"
    },
    "url": "https://therickandmortyapi.vercel.app/api/character/794"
  }
]
