[
  {
    "id": 95,
    "name": "Dipper and Mabel Mortys",
    "status": "unknown",
    "species": "Human",
    "location": {
      "name": "Citadel of Ricks",
      "url": "https://therickandmortyapi.vercel.app/api/location/3"
    },
    "image": "https://therickandmortyapi.vercel.app/api/character/avatar/95.jpeg",
    "episode": {
      "name": "The Rickshank Rickdemption",
      "url": "https://therickandmortyapi.vercel.app/api/episode/22"
    },
    "url": "https://therickandmortyapi.vercel.app/api/character/95"
  },
  {
    "id": 317,
    "name": "Shmlonathan Shmlower",
    "status": "Alive",
    "species": "Human",
    "location": {
      "name": "Interdimensional Cable",
      "url": "https://therickandmortyapi.vercel.app/api/location/6"
    },
    "image": "https://therickandmortyapi.vercel.app/api/character/avatar/317.jpeg",
    "episode": {
      "name": "Rixty Minutes",
      "url": "https://therickandmortyapi.vercel.app/api/episode/8"
    },
    "url": "https://therickandmortyapi.vercel.app/api/character/317"
  },
  {
    "id": 559,
    "name": "Gramuflackian Anchorman",
    "status": "Dead",
    "species": "Alien",
    "location": {
      "name": "Gramuflack",
      "url": "https://therickandmortyapi.vercel.app/api/location/93"
    },
    "image": "https://therickandmortyapi.vercel.app/api/character/avatar/559.jpeg",
    "episode": {
      "name": "One Crew Over the Crewcoo's Morty",
      "url": "https://therickandmortyapi.vercel.app/api/episode/34"
    },
    "url": "https://therickandmortyapi.vercel.app/api/character/559"
  },
  {
    "id": 634,
    "name": "Train Cops Instructor",
    "status": "Dead",
    "species": "Human",
    "location": {
      "name": "Story Train",
      "url": "https://therickandmortyapi.vercel.app/api/location/96"
    },
    "image": "https://therickandmortyapi.vercel.app/api/character/avatar/634.jpeg",
    "episode": {
      "name": "Never Ricking Morty",
      "url": "https://therickandmortyapi.vercel.app/api/episode/37"
    },
    "url": "https://therickandmortyapi.vercel.app/api/character/634"
  },
  {
    "id": 687,
    "name": "Scarecrow Rick",
    "status": "Dead",
    "species": "Robot",
    "location": {
      "name": "Earth (Replacement Dimension)",
      "url": "https://therickandmortyapi.vercel.app/api/location/20"
    },
    "image": "https://therickandmortyapi.vercel.app/api/character/avatar/687.jpeg",
    "episode": {
      "name": "Mortyplicity",
      "url": "https://therickandmortyapi.vercel.app/api/episode/43"
    },
    "url": "https://therickandmortyapi.vercel.app/api/character/687"
  },
  {
    "id": 753,
    "name": "Space Cruiser",
    "status": "Alive",
    "species": "Robot",
    "location": {
      "name": "Earth (Replacement Dimension)",
      "url": "https://therickandmortyapi.vercel.app/api/location/20"
    },
    "image": "https://therickandmortyapi.vercel.app/api/character/avatar/753.jpeg",
    "episode": {
      "name": "The Ricks Must Be Crazy",
      "url": "https://therickandmortyapi.vercel.app/api/episode/17"
    },
    "url": "https://therickandmortyapi.vercel.app/api/character/753"
  }
]
