[
  {
    "id": 115,
    "name": "Ethan",
    "status": "Alive",
    "species": "Human",
    "location": {
      "name": "Earth (Replacement Dimension)",
      "url": "https://therickandmortyapi.vercel.app/api/location/20"
    },
    "image": "https://therickandmortyapi.vercel.app/api/character/avatar/115.jpeg",
    "episode": {
      "name": "Get Schwifty",
      "url": "https://therickandmortyapi.vercel.app/api/episode/16"
    },
    "url": "https://therickandmortyapi.vercel.app/api/character/115"
  },
  {
    "id": 133,
    "name": "Garblovian",
    "status": "Alive",
    "species": "Alien",
    "location": {
      "name": "unknown",
      "url": ""
    },
    "image": "https://therickandmortyapi.vercel.app/api/character/avatar/133.jpeg",
    "episode": {
      "name": "Mortynight Run",
      "url": "https://therickandmortyapi.vercel.app/api/episode/13"
    },
    "url": "https://therickandmortyapi.vercel.app/api/character/133"
  },
  {
    "id": 303,
    "name": "Samantha",
    "status": "Alive",
    "species": "Human",
    "location": {
      "name": "Earth (C-137)",
      "url": "https://therickandmortyapi.vercel.app/api/location/1"
    },
    "image": "https://therickandmortyapi.vercel.app/api/character/avatar/303.jpeg",
    "episode": {
      "name": "Meeseeks and Destroy",
      "url": "https://therickandmortyapi.vercel.app/api/episode/5"
    },
    "url": "https://therickandmortyapi.vercel.app/api/character/303"
  },
  {
    "id": 338,
    "name": "Summer Smith",
    "status": "Alive",
    "species": "Human",
    "location": {
      "name": "Earth (C-137)",
      "url": "https://therickandmortyapi.vercel.app/api/location/1"
    },
    "image": "https://therickandmortyapi.vercel.app/api/character/avatar/338.jpeg",
    "episode": {
      "name": "Pilot",
      "url": "https://therickandmortyapi.vercel.app/api/episode/1"
    },
    "url": "https://therickandmortyapi.vercel.app/api/character/338"
  },
  {
    "id": 654,
    "name": "Plane Crash Survivor",
    "status": "unknown",
    "species": "Human",
    "location": {
      "name": "Near-Duplicate Reality",
      "url": "https://therickandmortyapi.vercel.app/api/location/104"
    },
    "image": "https://therickandmortyapi.vercel.app/api/character/avatar/654.jpeg",
    "episode": {
      "name": "The Vat of Acid Episode",
      "url": "https://therickandmortyapi.vercel.app/api/episode/39"
    },
    "url": "https://therickandmortyapi.vercel.app/api/character/654"
  },
  {
    "id": 792,
    "name": "Alien Crow",
    "status": "Dead",
    "species": "Alien",
    "location": {
      "name": "Avian Planet",
      "url": "https://therickandmortyapi.vercel.app/api/location/122"
    },
    "image": "https://therickandmortyapi.vercel.app/api/character/avatar/792.jpeg",
    "episode": {
      "name": "Forgetting Sarick Mortshall",
      "url": "https://therickandmortyapi.vercel.app/api/episode/50"
    },
    "url": "https://therickandmortyapi.vercel.app/api/character/792"
  }
]
