[
  {
    "id": 142,
    "name": "Gibble Snake",
    "status": "Dead",
    "species": "Alien",
    "location": {
      "name": "Resort Planet",
      "url": "https://therickandmortyapi.vercel.app/api/location/37"
    },
    "image": "https://raw.githubusercontent.com/iswilljr/rick-and-morty-api/master/src/images/142.jpeg",
    "episode": {
      "name": "The Whirly Dirly Conspiracy",
      "url": "https://therickandmortyapi.vercel.app/api/episode/26"
    },
    "url": "https://therickandmortyapi.vercel.app/api/character/142"
  },
  {
    "id": 275,
    "name": "Randy Dicknose",
    "status": "Alive",
    "species": "Human",
    "location": {
      "name": "Interdimensional Cable",
      "url": "https://therickandmortyapi.vercel.app/api/location/6"
    },
    "image": "https://raw.githubusercontent.com/iswilljr/rick-and-morty-api/master/src/images/275.jpeg",
    "episode": {
      "name": "Interdimensional Cable 2: Tempting Fate",
      "url": "https://therickandmortyapi.vercel.app/api/episode/19"
    },
    "url": "https://therickandmortyapi.vercel.app/api/character/275"
  },
  {
    "id": 305,
    "name": "Scary Glenn",
    "status": "Alive",
    "species": "Mythological Creature",
    "location": {
      "name": "Mr. Goldenfold's dream",
      "url": "https://therickandmortyapi.vercel.app/api/location/18"
    },
    "image": "https://raw.githubusercontent.com/iswilljr/rick-and-morty-api/master/src/images/305.jpeg",
    "episode": {
      "name": "Lawnmower Dog",
      "url": "https://therickandmortyapi.vercel.app/api/episode/2"
    },
    "url": "https://therickandmortyapi.vercel.app/api/character/305"
  },
  {
    "id": 461,
    "name": "Communication's Responsible Rick",
    "status": "Dead",
    "species": "Human",
    "location": {
      "name": "Citadel of Ricks",
      "url": "https://therickandmortyapi.vercel.app/api/location/3"
    },
    "image": "https://raw.githubusercontent.com/iswilljr/rick-and-morty-api/master/src/images/461.jpeg",
    "episode": {
      "name": "The Rickshank Rickdemption",
      "url": "https://therickandmortyapi.vercel.app/api/episode/22"
    },
    "url": "https://therickandmortyapi.vercel.app/api/character/461"
  },
  {
    "id": 504,
    "name": "Fascist Shrimp Rick’s Clone",
    "status": "Dead",
    "species": "Animal",
    "location": {
      "name": "Earth (Fascist Shrimp Dimension)",
      "url": "https://therickandmortyapi.vercel.app/api/location/80"
    },
    "image": "https://raw.githubusercontent.com/iswilljr/rick-and-morty-api/master/src/images/504.jpeg",
    "episode": {
      "name": "Edge of Tomorty: Rick, Die, Rickpeat",
      "url": "https://therickandmortyapi.vercel.app/api/episode/32"
    },
    "url": "https://therickandmortyapi.vercel.app/api/character/504"
  },
  {
    "id": 534,
    "name": "Tony's Dad",
    "status": "Alive",
    "species": "Alien",
    "location": {
      "name": "Earth (Replacement Dimension)",
      "url": "https://therickandmortyapi.vercel.app/api/location/20"
    },
    "image": "https://raw.githubusercontent.com/iswilljr/rick-and-morty-api/master/src/images/534.jpeg",
    "episode": {
      "name": "The Old Man and the Seat",
      "url": "https://therickandmortyapi.vercel.app/api/episode/33"
    },
    "url": "https://therickandmortyapi.vercel.app/api/character/534"
  }
]
