[
  {
    "id": 283,
    "name": "Rick D. Sanchez III",
    "status": "Dead",
    "species": "Human",
    "location": {
      "name": "Citadel of Ricks",
      "url": "https://therickandmortyapi.vercel.app/api/location/3"
    },
    "image": "https://raw.githubusercontent.com/iswilljr/rick-and-morty-api/master/src/images/283.jpeg",
    "episode": {
      "name": "The Ricklantis Mixup",
      "url": "https://therickandmortyapi.vercel.app/api/episode/28"
    },
    "url": "https://therickandmortyapi.vercel.app/api/character/283"
  },
  {
    "id": 333,
    "name": "Stair Goblin",
    "status": "Alive",
    "species": "Mythological Creature",
    "location": {
      "name": "Fantasy World",
      "url": "https://therickandmortyapi.vercel.app/api/location/48"
    },
    "image": "https://raw.githubusercontent.com/iswilljr/rick-and-morty-api/master/src/images/333.jpeg",
    "episode": {
      "name": "Meeseeks and Destroy",
      "url": "https://therickandmortyapi.vercel.app/api/episode/5"
    },
    "url": "https://therickandmortyapi.vercel.app/api/character/333"
  },
  {
    "id": 354,
    "name": "Toby Matthews",
    "status": "Alive",
    "species": "Human",
    "location": {
      "name": "Earth (Replacement Dimension)",
      "url": "https://therickandmortyapi.vercel.app/api/location/20"
    },
    "image": "https://raw.githubusercontent.com/iswilljr/rick-and-morty-api/master/src/images/354.jpeg",
    "episode": {
      "name": "Big Trouble in Little Sanchez",
      "url": "https://therickandmortyapi.vercel.app/api/episode/18"
    },
    "url": "https://therickandmortyapi.vercel.app/api/character/354"
  },
  {
    "id": 557,
    "name": "Ventriloquiver",
    "status": "Alive",
    "species": "Humanoid",
    "location": {
      "name": "Heistotron Base",
      "url": "https://therickandmortyapi.vercel.app/api/location/89"
    },
    "image": "https://raw.githubusercontent.com/iswilljr/rick-and-morty-api/master/src/images/557.jpeg",
    "episode": {
      "name": "One Crew Over the Crewcoo's Morty",
      "url": "https://therickandmortyapi.vercel.app/api/episode/34"
    },
    "url": "https://therickandmortyapi.vercel.app/api/character/557"
  },
  {
    "id": 629,
    "name": "Summer Smith",
    "status": "Alive",
    "species": "Human",
    "location": {
      "name": "Morty’s Story",
      "url": "https://therickandmortyapi.vercel.app/api/location/99"
    },
    "image": "https://raw.githubusercontent.com/iswilljr/rick-and-morty-api/master/src/images/629.jpeg",
    "episode": {
      "name": "Never Ricking Morty",
      "url": "https://therickandmortyapi.vercel.app/api/episode/37"
    },
    "url": "https://therickandmortyapi.vercel.app/api/character/629"
  },
  {
    "id": 655,
    "name": "Heroine Keith",
    "status": "Alive",
    "species": "Human",
    "location": {
      "name": "Merged Universe",
      "url": "https://therickandmortyapi.vercel.app/api/location/103"
    },
    "image": "https://raw.githubusercontent.com/iswilljr/rick-and-morty-api/master/src/images/655.jpeg",
    "episode": {
      "name": "The Vat of Acid Episode",
      "url": "https://therickandmortyapi.vercel.app/api/episode/39"
    },
    "url": "https://therickandmortyapi.vercel.app/api/character/655"
  }
]
