[
  {
    "id": 258,
    "name": "Pawnshop Clerk",
    "status": "Alive",
    "species": "Alien",
    "location": {
      "name": "Pawn Shop Planet",
      "url": "https://therickandmortyapi.vercel.app/api/location/55"
    },
    "image": "https://therickandmortyapi.vercel.app/api/character/avatar/258.jpeg",
    "episode": {
      "name": "Raising Gazorpazorp",
      "url": "https://therickandmortyapi.vercel.app/api/episode/7"
    },
    "url": "https://therickandmortyapi.vercel.app/api/character/258"
  },
  {
    "id": 611,
    "name": "Leah",
    "status": "Alive",
    "species": "unknown",
    "location": {
      "name": "Story Train",
      "url": "https://therickandmortyapi.vercel.app/api/location/96"
    },
    "image": "https://therickandmortyapi.vercel.app/api/character/avatar/611.jpeg",
    "episode": {
      "name": "Never Ricking Morty",
      "url": "https://therickandmortyapi.vercel.app/api/episode/37"
    },
    "url": "https://therickandmortyapi.vercel.app/api/character/611"
  },
  {
    "id": 629,
    "name": "Summer Smith",
    "status": "Alive",
    "species": "Human",
    "location": {
      "name": "Morty’s Story",
      "url": "https://therickandmortyapi.vercel.app/api/location/99"
    },
    "image": "https://therickandmortyapi.vercel.app/api/character/avatar/629.jpeg",
    "episode": {
      "name": "Never Ricking Morty",
      "url": "https://therickandmortyapi.vercel.app/api/episode/37"
    },
    "url": "https://therickandmortyapi.vercel.app/api/character/629"
  },
  {
    "id": 630,
    "name": "Morty Smith",
    "status": "Alive",
    "species": "Human",
    "location": {
      "name": "Story Train",
      "url": "https://therickandmortyapi.vercel.app/api/location/96"
    },
    "image": "https://therickandmortyapi.vercel.app/api/character/avatar/630.jpeg",
    "episode": {
      "name": "Never Ricking Morty",
      "url": "https://therickandmortyapi.vercel.app/api/episode/37"
    },
    "url": "https://therickandmortyapi.vercel.app/api/character/630"
  },
  {
    "id": 695,
    "name": "Glockenspiel Summer",
    "status": "Dead",
    "species": "Robot",
    "location": {
      "name": "Earth (Replacement Dimension)",
      "url": "https://therickandmortyapi.vercel.app/api/location/20"
    },
    "image": "https://therickandmortyapi.vercel.app/api/character/avatar/695.jpeg",
    "episode": {
      "name": "Mortyplicity",
      "url": "https://therickandmortyapi.vercel.app/api/episode/43"
    },
    "url": "https://therickandmortyapi.vercel.app/api/character/695"
  },
  {
    "id": 796,
    "name": "Sarge",
    "status": "Alive",
    "species": "Alien",
    "location": {
      "name": "Normal Size Bug Dimension",
      "url": "https://therickandmortyapi.vercel.app/api/location/123"
    },
    "image": "https://therickandmortyapi.vercel.app/api/character/avatar/796.jpeg",
    "episode": {
      "name": "Gotron Jerrysis Rickvangelion",
      "url": "https://therickandmortyapi.vercel.app/api/episode/48"
    },
    "url": "https://therickandmortyapi.vercel.app/api/character/796"
  }
]
