[
  {
    "id": 4,
    "name": "Beth Smith",
    "status": "Alive",
    "species": "Human",
    "location": {
      "name": "Earth (Replacement Dimension)",
      "url": "https://therickandmortyapi.vercel.app/api/location/20"
    },
    "image": "https://raw.githubusercontent.com/iswilljr/rick-and-morty-api/master/src/images/4.jpeg",
    "episode": {
      "name": "Rick Potion #9",
      "url": "https://therickandmortyapi.vercel.app/api/episode/6"
    },
    "url": "https://therickandmortyapi.vercel.app/api/character/4"
  },
  {
    "id": 45,
    "name": "Bill",
    "status": "Alive",
    "species": "Human",
    "location": {
      "name": "Earth (C-137)",
      "url": "https://therickandmortyapi.vercel.app/api/location/1"
    },
    "image": "https://raw.githubusercontent.com/iswilljr/rick-and-morty-api/master/src/images/45.jpeg",
    "episode": {
      "name": "Anatomy Park",
      "url": "https://therickandmortyapi.vercel.app/api/episode/3"
    },
    "url": "https://therickandmortyapi.vercel.app/api/character/45"
  },
  {
    "id": 125,
    "name": "Flansian",
    "status": "Alive",
    "species": "Alien",
    "location": {
      "name": "Planet Squanch",
      "url": "https://therickandmortyapi.vercel.app/api/location/35"
    },
    "image": "https://raw.githubusercontent.com/iswilljr/rick-and-morty-api/master/src/images/125.jpeg",
    "episode": {
      "name": "Big Trouble in Little Sanchez",
      "url": "https://therickandmortyapi.vercel.app/api/episode/18"
    },
    "url": "https://therickandmortyapi.vercel.app/api/character/125"
  },
  {
    "id": 290,
    "name": "Rick Sanchez",
    "status": "Dead",
    "species": "Human",
    "location": {
      "name": "Earth (Evil Rick's Target Dimension)",
      "url": "https://therickandmortyapi.vercel.app/api/location/34"
    },
    "image": "https://raw.githubusercontent.com/iswilljr/rick-and-morty-api/master/src/images/290.jpeg",
    "episode": {
      "name": "Close Rick-counters of the Rick Kind",
      "url": "https://therickandmortyapi.vercel.app/api/episode/10"
    },
    "url": "https://therickandmortyapi.vercel.app/api/character/290"
  },
  {
    "id": 327,
    "name": "Slow Mobius",
    "status": "Alive",
    "species": "Humanoid",
    "location": {
      "name": "Earth (Replacement Dimension)",
      "url": "https://therickandmortyapi.vercel.app/api/location/20"
    },
    "image": "https://raw.githubusercontent.com/iswilljr/rick-and-morty-api/master/src/images/327.jpeg",
    "episode": {
      "name": "Ricksy Business",
      "url": "https://therickandmortyapi.vercel.app/api/episode/11"
    },
    "url": "https://therickandmortyapi.vercel.app/api/character/327"
  },
  {
    "id": 663,
    "name": "Reggie",
    "status": "Dead",
    "species": "Mythological Creature",
    "location": {
      "name": "Gaia",
      "url": "https://therickandmortyapi.vercel.app/api/location/106"
    },
    "image": "https://raw.githubusercontent.com/iswilljr/rick-and-morty-api/master/src/images/663.jpeg",
    "episode": {
      "name": "Childrick of Mort",
      "url": "https://therickandmortyapi.vercel.app/api/episode/40"
    },
    "url": "https://therickandmortyapi.vercel.app/api/character/663"
  }
]
