[
  {
    "id": 96,
    "name": "Tuberculosis",
    "status": "Dead",
    "species": "Disease",
    "location": {
      "name": "Anatomy Park",
      "url": "https://therickandmortyapi.vercel.app/api/location/5"
    },
    "image": "https://raw.githubusercontent.com/iswilljr/rick-and-morty-api/master/src/images/96.jpeg",
    "episode": {
      "name": "Anatomy Park",
      "url": "https://therickandmortyapi.vercel.app/api/episode/3"
    },
    "url": "https://therickandmortyapi.vercel.app/api/character/96"
  },
  {
    "id": 99,
    "name": "Hepatitis C",
    "status": "Dead",
    "species": "Disease",
    "location": {
      "name": "Anatomy Park",
      "url": "https://therickandmortyapi.vercel.app/api/location/5"
    },
    "image": "https://raw.githubusercontent.com/iswilljr/rick-and-morty-api/master/src/images/99.jpeg",
    "episode": {
      "name": "Anatomy Park",
      "url": "https://therickandmortyapi.vercel.app/api/episode/3"
    },
    "url": "https://therickandmortyapi.vercel.app/api/character/99"
  },
  {
    "id": 336,
    "name": "Steven Phillips",
    "status": "Alive",
    "species": "Alien",
    "location": {
      "name": "Unity's Planet",
      "url": "https://therickandmortyapi.vercel.app/api/location/28"
    },
    "image": "https://raw.githubusercontent.com/iswilljr/rick-and-morty-api/master/src/images/336.jpeg",
    "episode": {
      "name": "Auto Erotic Assimilation",
      "url": "https://therickandmortyapi.vercel.app/api/episode/14"
    },
    "url": "https://therickandmortyapi.vercel.app/api/character/336"
  },
  {
    "id": 460,
    "name": "Traflorkian Journalist",
    "status": "Alive",
    "species": "Alien",
    "location": {
      "name": "St. Gloopy Noops Hospital",
      "url": "https://therickandmortyapi.vercel.app/api/location/16"
    },
    "image": "https://raw.githubusercontent.com/iswilljr/rick-and-morty-api/master/src/images/460.jpeg",
    "episode": {
      "name": "Interdimensional Cable 2: Tempting Fate",
      "url": "https://therickandmortyapi.vercel.app/api/episode/19"
    },
    "url": "https://therickandmortyapi.vercel.app/api/character/460"
  },
  {
    "id": 802,
    "name": "26 Years Old Morty",
    "status": "Dead",
    "species": "Human",
    "location": {
      "name": "Citadel of Ricks",
      "url": "https://therickandmortyapi.vercel.app/api/location/3"
    },
    "image": "https://raw.githubusercontent.com/iswilljr/rick-and-morty-api/master/src/images/802.jpeg",
    "episode": {
      "name": "Rickmurai Jack",
      "url": "https://therickandmortyapi.vercel.app/api/episode/51"
    },
    "url": "https://therickandmortyapi.vercel.app/api/character/802"
  },
  {
    "id": 812,
    "name": "Deformed Morty",
    "status": "Dead",
    "species": "Humanoid",
    "location": {
      "name": "Citadel of Ricks",
      "url": "https://therickandmortyapi.vercel.app/api/location/3"
    },
    "image": "https://raw.githubusercontent.com/iswilljr/rick-and-morty-api/master/src/images/812.jpeg",
    "episode": {
      "name": "Rickmurai Jack",
      "url": "https://therickandmortyapi.vercel.app/api/episode/51"
    },
    "url": "https://therickandmortyapi.vercel.app/api/character/812"
  }
]
