[
  {
    "id": 139,
    "name": "General Store Owner",
    "status": "Dead",
    "species": "Alien",
    "location": {
      "name": "Purge Planet",
      "url": "https://therickandmortyapi.vercel.app/api/location/9"
    },
    "image": "https://raw.githubusercontent.com/iswilljr/rick-and-morty-api/master/src/images/139.jpeg",
    "episode": {
      "name": "Look Who's Purging Now",
      "url": "https://therickandmortyapi.vercel.app/api/episode/20"
    },
    "url": "https://therickandmortyapi.vercel.app/api/character/139"
  },
  {
    "id": 358,
    "name": "Tophat Jones",
    "status": "Dead",
    "species": "Mythological Creature",
    "location": {
      "name": "Interdimensional Cable",
      "url": "https://therickandmortyapi.vercel.app/api/location/6"
    },
    "image": "https://raw.githubusercontent.com/iswilljr/rick-and-morty-api/master/src/images/358.jpeg",
    "episode": {
      "name": "Rixty Minutes",
      "url": "https://therickandmortyapi.vercel.app/api/episode/8"
    },
    "url": "https://therickandmortyapi.vercel.app/api/character/358"
  },
  {
    "id": 384,
    "name": "Yellow Headed Doctor",
    "status": "Alive",
    "species": "Alien",
    "location": {
      "name": "St. Gloopy Noops Hospital",
      "url": "https://therickandmortyapi.vercel.app/api/location/16"
    },
    "image": "https://raw.githubusercontent.com/iswilljr/rick-and-morty-api/master/src/images/384.jpeg",
    "episode": {
      "name": "Interdimensional Cable 2: Tempting Fate",
      "url": "https://therickandmortyapi.vercel.app/api/episode/19"
    },
    "url": "https://therickandmortyapi.vercel.app/api/character/384"
  },
  {
    "id": 415,
    "name": "Pro trunk people marriage guy",
    "status": "Alive",
    "species": "Human",
    "location": {
      "name": "Interdimensional Cable",
      "url": "https://therickandmortyapi.vercel.app/api/location/6"
    },
    "image": "https://raw.githubusercontent.com/iswilljr/rick-and-morty-api/master/src/images/415.jpeg",
    "episode": {
      "name": "Rixty Minutes",
      "url": "https://therickandmortyapi.vercel.app/api/episode/8"
    },
    "url": "https://therickandmortyapi.vercel.app/api/character/415"
  },
  {
    "id": 704,
    "name": "Squid Costume Beth",
    "status": "Dead",
    "species": "Robot",
    "location": {
      "name": "Earth (Replacement Dimension)",
      "url": "https://therickandmortyapi.vercel.app/api/location/20"
    },
    "image": "https://raw.githubusercontent.com/iswilljr/rick-and-morty-api/master/src/images/704.jpeg",
    "episode": {
      "name": "Mortyplicity",
      "url": "https://therickandmortyapi.vercel.app/api/episode/43"
    },
    "url": "https://therickandmortyapi.vercel.app/api/character/704"
  },
  {
    "id": 797,
    "name": "Slartivartian",
    "status": "Dead",
    "species": "Alien",
    "location": {
      "name": "Slartivart",
      "url": "https://therickandmortyapi.vercel.app/api/location/124"
    },
    "image": "https://raw.githubusercontent.com/iswilljr/rick-and-morty-api/master/src/images/797.jpeg",
    "episode": {
      "name": "A Rickconvenient Mort",
      "url": "https://therickandmortyapi.vercel.app/api/episode/44"
    },
    "url": "https://therickandmortyapi.vercel.app/api/character/797"
  }
]
