[
  {
    "id": 91,
    "name": "David Letterman",
    "status": "Alive",
    "species": "Human",
    "type": "",
    "gender": "Male",
    "location": {
      "name": "Earth (C-500A)",
      "url": "https://therickandmortyapi.vercel.app/api/location/23"
    },
    "origin": {
      "name": "Earth (C-500A)",
      "url": "https://therickandmortyapi.vercel.app/api/location/23"
    },
    "image": "https://therickandmortyapi.vercel.app/api/character/avatar/91.jpeg",
    "episode": {
      "id": 8,
      "name": "Rixty Minutes",
      "air_date": "March 17, 2014",
      "episode": "S01E08",
      "characters": [
        "https://therickandmortyapi.vercel.app/api/character/1",
        "https://therickandmortyapi.vercel.app/api/character/2",
        "https://therickandmortyapi.vercel.app/api/character/3",
        "https://therickandmortyapi.vercel.app/api/character/4",
        "https://therickandmortyapi.vercel.app/api/character/5",
        "https://therickandmortyapi.vercel.app/api/character/20",
        "https://therickandmortyapi.vercel.app/api/character/28",
        "https://therickandmortyapi.vercel.app/api/character/29",
        "https://therickandmortyapi.vercel.app/api/character/34",
        "https://therickandmortyapi.vercel.app/api/character/37",
        "https://therickandmortyapi.vercel.app/api/character/54",
        "https://therickandmortyapi.vercel.app/api/character/88",
        "https://therickandmortyapi.vercel.app/api/character/91",
        "https://therickandmortyapi.vercel.app/api/character/129",
        "https://therickandmortyapi.vercel.app/api/character/134",
        "https://therickandmortyapi.vercel.app/api/character/136",
        "https://therickandmortyapi.vercel.app/api/character/145",
        "https://therickandmortyapi.vercel.app/api/character/153",
        "https://therickandmortyapi.vercel.app/api/character/157",
        "https://therickandmortyapi.vercel.app/api/character/176",
        "https://therickandmortyapi.vercel.app/api/character/183",
        "https://therickandmortyapi.vercel.app/api/character/184",
        "https://therickandmortyapi.vercel.app/api/character/195",
        "https://therickandmortyapi.vercel.app/api/character/207",
        "https://therickandmortyapi.vercel.app/api/character/214",
        "https://therickandmortyapi.vercel.app/api/character/222",
        "https://therickandmortyapi.vercel.app/api/character/250",
        "https://therickandmortyapi.vercel.app/api/character/266",
        "https://therickandmortyapi.vercel.app/api/character/277",
        "https://therickandmortyapi.vercel.app/api/character/279",
        "https://therickandmortyapi.vercel.app/api/character/314",
        "https://therickandmortyapi.vercel.app/api/character/315",
        "https://therickandmortyapi.vercel.app/api/character/316",
        "https://therickandmortyapi.vercel.app/api/character/317",
        "https://therickandmortyapi.vercel.app/api/character/318",
        "https://therickandmortyapi.vercel.app/api/character/351",
        "https://therickandmortyapi.vercel.app/api/character/358",
        "https://therickandmortyapi.vercel.app/api/character/367",
        "https://therickandmortyapi.vercel.app/api/character/370",
        "https://therickandmortyapi.vercel.app/api/character/373",
        "https://therickandmortyapi.vercel.app/api/character/402",
        "https://therickandmortyapi.vercel.app/api/character/403",
        "https://therickandmortyapi.vercel.app/api/character/404",
        "https://therickandmortyapi.vercel.app/api/character/405",
        "https://therickandmortyapi.vercel.app/api/character/406",
        "https://therickandmortyapi.vercel.app/api/character/407",
        "https://therickandmortyapi.vercel.app/api/character/408",
        "https://therickandmortyapi.vercel.app/api/character/409",
        "https://therickandmortyapi.vercel.app/api/character/410",
        "https://therickandmortyapi.vercel.app/api/character/411",
        "https://therickandmortyapi.vercel.app/api/character/412",
        "https://therickandmortyapi.vercel.app/api/character/413",
        "https://therickandmortyapi.vercel.app/api/character/414",
        "https://therickandmortyapi.vercel.app/api/character/415",
        "https://therickandmortyapi.vercel.app/api/character/416",
        "https://therickandmortyapi.vercel.app/api/character/417",
        "https://therickandmortyapi.vercel.app/api/character/418"
      ],
      "url": "https://therickandmortyapi.vercel.app/api/episode/8",
      "created": "2017-11-10T07:56:34.543Z"
    },
    "url": "https://therickandmortyapi.vercel.app/api/character/91",
    "created": "2017-12-01T06:12:25.105Z"
  },
  {
    "id": 174,
    "name": "Jerry 5-126",
    "status": "Alive",
    "species": "Human",
    "type": "",
    "gender": "Male",
    "location": {
      "name": "Jerryboree",
      "url": "https://therickandmortyapi.vercel.app/api/location/44"
    },
    "origin": {
      "name": "Earth (5-126)",
      "url": "https://therickandmortyapi.vercel.app/api/location/17"
    },
    "image": "https://therickandmortyapi.vercel.app/api/character/avatar/174.jpeg",
    "episode": {
      "id": 13,
      "name": "Mortynight Run",
      "air_date": "August 2, 2015",
      "episode": "S02E02",
      "characters": [
        "https://therickandmortyapi.vercel.app/api/character/1",
        "https://therickandmortyapi.vercel.app/api/character/2",
        "https://therickandmortyapi.vercel.app/api/character/5",
        "https://therickandmortyapi.vercel.app/api/character/23",
        "https://therickandmortyapi.vercel.app/api/character/28",
        "https://therickandmortyapi.vercel.app/api/character/34",
        "https://therickandmortyapi.vercel.app/api/character/106",
        "https://therickandmortyapi.vercel.app/api/character/122",
        "https://therickandmortyapi.vercel.app/api/character/129",
        "https://therickandmortyapi.vercel.app/api/character/131",
        "https://therickandmortyapi.vercel.app/api/character/133",
        "https://therickandmortyapi.vercel.app/api/character/136",
        "https://therickandmortyapi.vercel.app/api/character/174",
        "https://therickandmortyapi.vercel.app/api/character/180",
        "https://therickandmortyapi.vercel.app/api/character/196",
        "https://therickandmortyapi.vercel.app/api/character/207",
        "https://therickandmortyapi.vercel.app/api/character/242",
        "https://therickandmortyapi.vercel.app/api/character/257",
        "https://therickandmortyapi.vercel.app/api/character/282",
        "https://therickandmortyapi.vercel.app/api/character/309",
        "https://therickandmortyapi.vercel.app/api/character/311",
        "https://therickandmortyapi.vercel.app/api/character/362",
        "https://therickandmortyapi.vercel.app/api/character/386",
        "https://therickandmortyapi.vercel.app/api/character/393",
        "https://therickandmortyapi.vercel.app/api/character/436",
        "https://therickandmortyapi.vercel.app/api/character/441",
        "https://therickandmortyapi.vercel.app/api/character/442",
        "https://therickandmortyapi.vercel.app/api/character/443",
        "https://therickandmortyapi.vercel.app/api/character/444",
        "https://therickandmortyapi.vercel.app/api/character/445",
        "https://therickandmortyapi.vercel.app/api/character/446",
        "https://therickandmortyapi.vercel.app/api/character/447",
        "https://therickandmortyapi.vercel.app/api/character/448",
        "https://therickandmortyapi.vercel.app/api/character/449",
        "https://therickandmortyapi.vercel.app/api/character/450",
        "https://therickandmortyapi.vercel.app/api/character/451"
      ],
      "url": "https://therickandmortyapi.vercel.app/api/episode/13",
      "created": "2017-11-10T07:56:35.055Z"
    },
    "url": "https://therickandmortyapi.vercel.app/api/character/174",
    "created": "2017-12-29T12:50:19.991Z"
  },
  {
    "id": 302,
    "name": "Ruben",
    "status": "Dead",
    "species": "Human",
    "type": "",
    "gender": "Male",
    "location": {
      "name": "Earth (C-137)",
      "url": "https://therickandmortyapi.vercel.app/api/location/1"
    },
    "origin": {
      "name": "Earth (C-137)",
      "url": "https://therickandmortyapi.vercel.app/api/location/1"
    },
    "image": "https://therickandmortyapi.vercel.app/api/character/avatar/302.jpeg",
    "episode": {
      "id": 3,
      "name": "Anatomy Park",
      "air_date": "December 16, 2013",
      "episode": "S01E03",
      "characters": [
        "https://therickandmortyapi.vercel.app/api/character/1",
        "https://therickandmortyapi.vercel.app/api/character/2",
        "https://therickandmortyapi.vercel.app/api/character/12",
        "https://therickandmortyapi.vercel.app/api/character/17",
        "https://therickandmortyapi.vercel.app/api/character/38",
        "https://therickandmortyapi.vercel.app/api/character/45",
        "https://therickandmortyapi.vercel.app/api/character/96",
        "https://therickandmortyapi.vercel.app/api/character/97",
        "https://therickandmortyapi.vercel.app/api/character/98",
        "https://therickandmortyapi.vercel.app/api/character/99",
        "https://therickandmortyapi.vercel.app/api/character/100",
        "https://therickandmortyapi.vercel.app/api/character/101",
        "https://therickandmortyapi.vercel.app/api/character/108",
        "https://therickandmortyapi.vercel.app/api/character/112",
        "https://therickandmortyapi.vercel.app/api/character/114",
        "https://therickandmortyapi.vercel.app/api/character/169",
        "https://therickandmortyapi.vercel.app/api/character/175",
        "https://therickandmortyapi.vercel.app/api/character/186",
        "https://therickandmortyapi.vercel.app/api/character/201",
        "https://therickandmortyapi.vercel.app/api/character/268",
        "https://therickandmortyapi.vercel.app/api/character/300",
        "https://therickandmortyapi.vercel.app/api/character/302",
        "https://therickandmortyapi.vercel.app/api/character/338",
        "https://therickandmortyapi.vercel.app/api/character/356"
      ],
      "url": "https://therickandmortyapi.vercel.app/api/episode/3",
      "created": "2017-11-10T07:56:34.022Z"
    },
    "url": "https://therickandmortyapi.vercel.app/api/character/302",
    "created": "2018-01-05T09:03:21.824Z"
  },
  {
    "id": 368,
    "name": "Truth Tortoise",
    "status": "unknown",
    "species": "Mythological Creature",
    "type": "Omniscient being",
    "gender": "Male",
    "location": {
      "name": "unknown",
      "url": ""
    },
    "origin": {
      "name": "unknown",
      "url": ""
    },
    "image": "https://therickandmortyapi.vercel.app/api/character/avatar/368.jpeg",
    "episode": {
      "id": 29,
      "name": "Morty's Mind Blowers",
      "air_date": "September 17, 2017",
      "episode": "S03E08",
      "characters": [
        "https://therickandmortyapi.vercel.app/api/character/1",
        "https://therickandmortyapi.vercel.app/api/character/2",
        "https://therickandmortyapi.vercel.app/api/character/3",
        "https://therickandmortyapi.vercel.app/api/character/4",
        "https://therickandmortyapi.vercel.app/api/character/5",
        "https://therickandmortyapi.vercel.app/api/character/33",
        "https://therickandmortyapi.vercel.app/api/character/67",
        "https://therickandmortyapi.vercel.app/api/character/147",
        "https://therickandmortyapi.vercel.app/api/character/149",
        "https://therickandmortyapi.vercel.app/api/character/180",
        "https://therickandmortyapi.vercel.app/api/character/242",
        "https://therickandmortyapi.vercel.app/api/character/244",
        "https://therickandmortyapi.vercel.app/api/character/251",
        "https://therickandmortyapi.vercel.app/api/character/272",
        "https://therickandmortyapi.vercel.app/api/character/329",
        "https://therickandmortyapi.vercel.app/api/character/368",
        "https://therickandmortyapi.vercel.app/api/character/377",
        "https://therickandmortyapi.vercel.app/api/character/390",
        "https://therickandmortyapi.vercel.app/api/character/490",
        "https://therickandmortyapi.vercel.app/api/character/491"
      ],
      "url": "https://therickandmortyapi.vercel.app/api/episode/29",
      "created": "2017-11-10T07:56:36.726Z"
    },
    "url": "https://therickandmortyapi.vercel.app/api/character/368",
    "created": "2018-01-10T14:14:35.885Z"
  },
  {
    "id": 534,
    "name": "Tony's Dad",
    "status": "Alive",
    "species": "Alien",
    "type": "",
    "gender": "Male",
    "location": {
      "name": "Earth (Replacement Dimension)",
      "url": "https://therickandmortyapi.vercel.app/api/location/20"
    },
    "origin": {
      "name": "unknown",
      "url": ""
    },
    "image": "https://therickandmortyapi.vercel.app/api/character/avatar/534.jpeg",
    "episode": {
      "id": 33,
      "name": "The Old Man and the Seat",
      "air_date": "November 17, 2019",
      "episode": "S04E02",
      "characters": [
        "https://therickandmortyapi.vercel.app/api/character/1",
        "https://therickandmortyapi.vercel.app/api/character/2",
        "https://therickandmortyapi.vercel.app/api/character/3",
        "https://therickandmortyapi.vercel.app/api/character/4",
        "https://therickandmortyapi.vercel.app/api/character/5",
        "https://therickandmortyapi.vercel.app/api/character/525",
        "https://therickandmortyapi.vercel.app/api/character/526",
        "https://therickandmortyapi.vercel.app/api/character/527",
        "https://therickandmortyapi.vercel.app/api/character/528",
        "https://therickandmortyapi.vercel.app/api/character/529",
        "https://therickandmortyapi.vercel.app/api/character/530",
        "https://therickandmortyapi.vercel.app/api/character/531",
        "https://therickandmortyapi.vercel.app/api/character/532",
        "https://therickandmortyapi.vercel.app/api/character/533",
        "https://therickandmortyapi.vercel.app/api/character/534",
        "https://therickandmortyapi.vercel.app/api/character/535",
        "https://therickandmortyapi.vercel.app/api/character/536",
        "https://therickandmortyapi.vercel.app/api/character/537",
        "https://therickandmortyapi.vercel.app/api/character/538",
        "https://therickandmortyapi.vercel.app/api/character/539",
        "https://therickandmortyapi.vercel.app/api/character/540",
        "https://therickandmortyapi.vercel.app/api/character/541",
        "https://therickandmortyapi.vercel.app/api/character/542",
        "https://therickandmortyapi.vercel.app/api/character/543"
      ],
      "url": "https://therickandmortyapi.vercel.app/api/episode/33",
      "created": "2020-04-30T01:52:04.498Z"
    },
    "url": "https://therickandmortyapi.vercel.app/api/character/534",
    "created": "2020-05-02T08:52:06.880Z"
  },
  {
    "id": 772,
    "name": "Wrap-it-up Little Rick",
    "status": "Dead",
    "species": "Human",
    "type": "",
    "gender": "Male",
    "location": {
      "name": "Earth (Replacement Dimension)",
      "url": "https://therickandmortyapi.vercel.app/api/location/20"
    },
    "origin": {
      "name": "unknown",
      "url": ""
    },
    "image": "https://therickandmortyapi.vercel.app/api/character/avatar/772.jpeg",
    "episode": {
      "id": 48,
      "name": "Gotron Jerrysis Rickvangelion",
      "air_date": "August 1, 2021",
      "episode": "S05E07",
      "characters": [
        "https://therickandmortyapi.vercel.app/api/character/1",
        "https://therickandmortyapi.vercel.app/api/character/2",
        "https://therickandmortyapi.vercel.app/api/character/3",
        "https://therickandmortyapi.vercel.app/api/character/4",
        "https://therickandmortyapi.vercel.app/api/character/5",
        "https://therickandmortyapi.vercel.app/api/character/203",
        "https://therickandmortyapi.vercel.app/api/character/731",
        "https://therickandmortyapi.vercel.app/api/character/769",
        "https://therickandmortyapi.vercel.app/api/character/770",
        "https://therickandmortyapi.vercel.app/api/character/771",
        "https://therickandmortyapi.vercel.app/api/character/772",
        "https://therickandmortyapi.vercel.app/api/character/773",
        "https://therickandmortyapi.vercel.app/api/character/774",
        "https://therickandmortyapi.vercel.app/api/character/775",
        "https://therickandmortyapi.vercel.app/api/character/776",
        "https://therickandmortyapi.vercel.app/api/character/777",
        "https://therickandmortyapi.vercel.app/api/character/778",
        "https://therickandmortyapi.vercel.app/api/character/794",
        "https://therickandmortyapi.vercel.app/api/character/795",
        "https://therickandmortyapi.vercel.app/api/character/796",
        "https://therickandmortyapi.vercel.app/api/character/821"
      ],
      "url": "https://therickandmortyapi.vercel.app/api/episode/48",
      "created": "2021-10-15T12:00:24.104Z"
    },
    "url": "https://therickandmortyapi.vercel.app/api/character/772",
    "created": "2021-10-25T03:57:20.725Z"
  }
]
