[
  {
    "id": 10,
    "name": "Alan Rails",
    "status": "Dead",
    "species": "Human",
    "location": {
      "name": "Worldender's lair",
      "url": "https://therickandmortyapi.vercel.app/api/location/4"
    },
    "image": "https://therickandmortyapi.vercel.app/api/character/avatar/10.jpeg",
    "episode": {
      "name": "Vindicators 3: The Return of Worldender",
      "url": "https://therickandmortyapi.vercel.app/api/episode/25"
    },
    "url": "https://therickandmortyapi.vercel.app/api/character/10"
  },
  {
    "id": 109,
    "name": "Duck With Muscles",
    "status": "Dead",
    "species": "Alien",
    "location": {
      "name": "Earth (Replacement Dimension)",
      "url": "https://therickandmortyapi.vercel.app/api/location/20"
    },
    "image": "https://therickandmortyapi.vercel.app/api/character/avatar/109.jpeg",
    "episode": {
      "name": "Total Rickall",
      "url": "https://therickandmortyapi.vercel.app/api/episode/15"
    },
    "url": "https://therickandmortyapi.vercel.app/api/character/109"
  },
  {
    "id": 205,
    "name": "Little Dipper",
    "status": "Alive",
    "species": "Humanoid",
    "location": {
      "name": "Interdimensional Cable",
      "url": "https://therickandmortyapi.vercel.app/api/location/6"
    },
    "image": "https://therickandmortyapi.vercel.app/api/character/avatar/205.jpeg",
    "episode": {
      "name": "Interdimensional Cable 2: Tempting Fate",
      "url": "https://therickandmortyapi.vercel.app/api/episode/19"
    },
    "url": "https://therickandmortyapi.vercel.app/api/character/205"
  },
  {
    "id": 294,
    "name": "Ricktiminus Sancheziminius",
    "status": "Dead",
    "species": "Human",
    "location": {
      "name": "Rick's Memories",
      "url": "https://therickandmortyapi.vercel.app/api/location/126"
    },
    "image": "https://therickandmortyapi.vercel.app/api/character/avatar/294.jpeg",
    "episode": {
      "name": "Close Rick-counters of the Rick Kind",
      "url": "https://therickandmortyapi.vercel.app/api/episode/10"
    },
    "url": "https://therickandmortyapi.vercel.app/api/character/294"
  },
  {
    "id": 405,
    "name": "Trunkphobic suspenders guy",
    "status": "Alive",
    "species": "Human",
    "location": {
      "name": "Earth (Replacement Dimension)",
      "url": "https://therickandmortyapi.vercel.app/api/location/20"
    },
    "image": "https://therickandmortyapi.vercel.app/api/character/avatar/405.jpeg",
    "episode": {
      "name": "Lawnmower Dog",
      "url": "https://therickandmortyapi.vercel.app/api/episode/2"
    },
    "url": "https://therickandmortyapi.vercel.app/api/character/405"
  },
  {
    "id": 427,
    "name": "Phone-person",
    "status": "Alive",
    "species": "Humanoid",
    "location": {
      "name": "Earth (Phone Dimension)",
      "url": "https://therickandmortyapi.vercel.app/api/location/72"
    },
    "image": "https://therickandmortyapi.vercel.app/api/character/avatar/427.jpeg",
    "episode": {
      "name": "Close Rick-counters of the Rick Kind",
      "url": "https://therickandmortyapi.vercel.app/api/episode/10"
    },
    "url": "https://therickandmortyapi.vercel.app/api/character/427"
  }
]
