[
  {
    "id": 77,
    "name": "Cowboy Morty",
    "status": "Alive",
    "species": "Human",
    "location": {
      "name": "Citadel of Ricks",
      "url": "https://therickandmortyapi.vercel.app/api/location/3"
    },
    "image": "https://therickandmortyapi.vercel.app/api/character/avatar/77.jpeg",
    "episode": {
      "name": "Close Rick-counters of the Rick Kind",
      "url": "https://therickandmortyapi.vercel.app/api/episode/10"
    },
    "url": "https://therickandmortyapi.vercel.app/api/character/77"
  },
  {
    "id": 129,
    "name": "Fulgora",
    "status": "Alive",
    "species": "Human",
    "location": {
      "name": "Interdimensional Cable",
      "url": "https://therickandmortyapi.vercel.app/api/location/6"
    },
    "image": "https://therickandmortyapi.vercel.app/api/character/avatar/129.jpeg",
    "episode": {
      "name": "Rixty Minutes",
      "url": "https://therickandmortyapi.vercel.app/api/episode/8"
    },
    "url": "https://therickandmortyapi.vercel.app/api/character/129"
  },
  {
    "id": 249,
    "name": "Mrs. Sanchez",
    "status": "unknown",
    "species": "Human",
    "location": {
      "name": "unknown",
      "url": ""
    },
    "image": "https://therickandmortyapi.vercel.app/api/character/avatar/249.jpeg",
    "episode": {
      "name": "Pilot",
      "url": "https://therickandmortyapi.vercel.app/api/episode/1"
    },
    "url": "https://therickandmortyapi.vercel.app/api/character/249"
  },
  {
    "id": 251,
    "name": "Nancy",
    "status": "Alive",
    "species": "Human",
    "location": {
      "name": "Earth (Replacement Dimension)",
      "url": "https://therickandmortyapi.vercel.app/api/location/20"
    },
    "image": "https://therickandmortyapi.vercel.app/api/character/avatar/251.jpeg",
    "episode": {
      "name": "Rick Potion #9",
      "url": "https://therickandmortyapi.vercel.app/api/episode/6"
    },
    "url": "https://therickandmortyapi.vercel.app/api/character/251"
  },
  {
    "id": 542,
    "name": "Mountain Sweat Jerry",
    "status": "Alive",
    "species": "Human",
    "location": {
      "name": "Globaflyn",
      "url": "https://therickandmortyapi.vercel.app/api/location/87"
    },
    "image": "https://therickandmortyapi.vercel.app/api/character/avatar/542.jpeg",
    "episode": {
      "name": "The Old Man and the Seat",
      "url": "https://therickandmortyapi.vercel.app/api/episode/33"
    },
    "url": "https://therickandmortyapi.vercel.app/api/character/542"
  },
  {
    "id": 665,
    "name": "Florflock",
    "status": "Alive",
    "species": "Humanoid",
    "location": {
      "name": "Gaia",
      "url": "https://therickandmortyapi.vercel.app/api/location/106"
    },
    "image": "https://therickandmortyapi.vercel.app/api/character/avatar/665.jpeg",
    "episode": {
      "name": "Childrick of Mort",
      "url": "https://therickandmortyapi.vercel.app/api/episode/40"
    },
    "url": "https://therickandmortyapi.vercel.app/api/character/665"
  }
]
