[
  {
    "id": 182,
    "name": "Jim",
    "status": "Alive",
    "species": "Human",
    "location": {
      "name": "Earth (Replacement Dimension)",
      "url": "https://therickandmortyapi.vercel.app/api/location/20"
    },
    "image": "https://therickandmortyapi.vercel.app/api/character/avatar/182.jpeg",
    "episode": {
      "name": "Get Schwifty",
      "url": "https://therickandmortyapi.vercel.app/api/episode/16"
    },
    "url": "https://therickandmortyapi.vercel.app/api/character/182"
  },
  {
    "id": 184,
    "name": "Jon",
    "status": "Alive",
    "species": "Alien",
    "location": {
      "name": "Interdimensional Cable",
      "url": "https://therickandmortyapi.vercel.app/api/location/6"
    },
    "image": "https://therickandmortyapi.vercel.app/api/character/avatar/184.jpeg",
    "episode": {
      "name": "Rixty Minutes",
      "url": "https://therickandmortyapi.vercel.app/api/episode/8"
    },
    "url": "https://therickandmortyapi.vercel.app/api/character/184"
  },
  {
    "id": 493,
    "name": "Secretary of the Interior",
    "status": "Alive",
    "species": "Human",
    "location": {
      "name": "Earth (Replacement Dimension)",
      "url": "https://therickandmortyapi.vercel.app/api/location/20"
    },
    "image": "https://therickandmortyapi.vercel.app/api/character/avatar/493.jpeg",
    "episode": {
      "name": "The Rickchurian Mortydate",
      "url": "https://therickandmortyapi.vercel.app/api/episode/31"
    },
    "url": "https://therickandmortyapi.vercel.app/api/character/493"
  },
  {
    "id": 535,
    "name": "Jeff",
    "status": "Alive",
    "species": "Human",
    "location": {
      "name": "Earth (Replacement Dimension)",
      "url": "https://therickandmortyapi.vercel.app/api/location/20"
    },
    "image": "https://therickandmortyapi.vercel.app/api/character/avatar/535.jpeg",
    "episode": {
      "name": "The Old Man and the Seat",
      "url": "https://therickandmortyapi.vercel.app/api/episode/33"
    },
    "url": "https://therickandmortyapi.vercel.app/api/character/535"
  },
  {
    "id": 560,
    "name": "Gramuflackian General",
    "status": "Dead",
    "species": "Alien",
    "location": {
      "name": "Gramuflack",
      "url": "https://therickandmortyapi.vercel.app/api/location/93"
    },
    "image": "https://therickandmortyapi.vercel.app/api/character/avatar/560.jpeg",
    "episode": {
      "name": "One Crew Over the Crewcoo's Morty",
      "url": "https://therickandmortyapi.vercel.app/api/episode/34"
    },
    "url": "https://therickandmortyapi.vercel.app/api/character/560"
  },
  {
    "id": 581,
    "name": "Anchosnake",
    "status": "Alive",
    "species": "Animal",
    "location": {
      "name": "Snake Planet",
      "url": "https://therickandmortyapi.vercel.app/api/location/78"
    },
    "image": "https://therickandmortyapi.vercel.app/api/character/avatar/581.jpeg",
    "episode": {
      "name": "Rattlestar Ricklactica",
      "url": "https://therickandmortyapi.vercel.app/api/episode/36"
    },
    "url": "https://therickandmortyapi.vercel.app/api/character/581"
  }
]
